{"id": "ben.devices.agilent34970A", "path": "/home/ben/ben/devices/agilent34970A/__init__.py", "mtime": 1508436996, "size": 29, "hash": "6406125368d9ba94fb677bc9aaf50d4a", "data_mtime": 1531737977, "dependencies": ["ben.devices.agilent34970A.a34970A", "builtins"], "suppressed": [], "child_modules": ["ben.devices.agilent34970A.a34970A"], "options": {"disallow_untyped_calls": false, "no_implicit_optional": false, "ignore_errors": false, "check_untyped_defs": false, "quick_and_dirty": false, "ignore_missing_imports": true, "disallow_any_explicit": false, "disallow_subclassing_any": false, "disallow_any_expr": false, "disallow_any_decorated": false, "strict_optional_whitelist": null, "warn_return_any": false, "disallow_any_unimported": false, "strict_optional": false, "strict_boolean": false, "disallow_untyped_decorators": false, "warn_no_return": true, "follow_imports": "silent", "disallow_untyped_defs": false, "platform": "linux", "show_none_errors": true, "disallow_any_generics": false}, "dep_prios": [5, 5], "interface_hash": "af15e22fa767a7ef611997a4c386b9f5", "version_id": "0.560", "ignore_all": true}
